models/__init__.py
models/logistic_regression_model.py
models/model_interface.py
models/nlp_model.py
models/random_forest_model.py
retry/__init__.py
retry/retry_decorator.py
templates/__init__.py
templates/logistic_regression_template.py
templates/nlp_template.py
templates/random_forest_template.py
tests/__init__.py
tests/test_diabetes_outcome_logistic_regression.py
tests/test_nlp.py
tests/test_random_forest.py
tests/test_roach_outcome_logical_regression.py
InsightfulAI-0.3.0a1.dist-info/LICENSE
InsightfulAI-0.3.0a1.dist-info/METADATA
InsightfulAI-0.3.0a1.dist-info/WHEEL
InsightfulAI-0.3.0a1.dist-info/top_level.txt
InsightfulAI-0.3.0a1.dist-info/RECORD
