Metadata-Version: 2.1
Name: InsightfulAI
Version: 0.3.0a1
Summary: A simple ML package for classification and regression
Author: Philip Thomas
Classifier: Programming Language :: Python :: 3
Classifier: License :: OSI Approved :: Apache Software License
Classifier: Operating System :: OS Independent
Requires-Python: >=3.6
License-File: LICENSE
Requires-Dist: scikit-learn
Requires-Dist: numpy
Requires-Dist: opentelemetry-api
Requires-Dist: opentelemetry-sdk
Requires-Dist: opentelemetry-instrumentation
Requires-Dist: asyncio
